music_assistant_models/__init__.py
music_assistant_models/api.py
music_assistant_models/auth.py
music_assistant_models/config_entries.py
music_assistant_models/constants.py
music_assistant_models/dsp.py
music_assistant_models/enums.py
music_assistant_models/errors.py
music_assistant_models/event.py
music_assistant_models/helpers.py
music_assistant_models/playback_progress_report.py
music_assistant_models/player.py
music_assistant_models/player_control.py
music_assistant_models/player_queue.py
music_assistant_models/provider.py
music_assistant_models/py.typed
music_assistant_models/queue_item.py
music_assistant_models/streamdetails.py
music_assistant_models/unique_list.py
music_assistant_models/media_items/__init__.py
music_assistant_models/media_items/audio_format.py
music_assistant_models/media_items/media_item.py
music_assistant_models/media_items/metadata.py
music_assistant_models/media_items/provider_mapping.py
music_assistant_models-1.1.95.dist-info/licenses/LICENSE
music_assistant_models-1.1.95.dist-info/METADATA
music_assistant_models-1.1.95.dist-info/WHEEL
music_assistant_models-1.1.95.dist-info/top_level.txt
music_assistant_models-1.1.95.dist-info/RECORD
